cv2/__init__.py
testcv2-0.0.1.dist-info/METADATA
testcv2-0.0.1.dist-info/WHEEL
testcv2-0.0.1.dist-info/top_level.txt
testcv2-0.0.1.dist-info/RECORD
